govdash/__init__.py
govdash-0.1.0.dist-info/WHEEL
govdash-0.1.0.dist-info/METADATA
govdash-0.1.0.dist-info/RECORD
