Metadata-Version: 2.1
Name: govdash
Version: 0.1.0
Summary: Gov styled components for Dash
Home-page: https://github.com/ellsphillips/govdash
License: MIT
Author: ellsphillips
Author-email: elliott.phillips.dev@gmail.com
Requires-Python: >=3.8,<4.0
Classifier: License :: OSI Approved :: MIT License
Classifier: Programming Language :: Python :: 3
Classifier: Programming Language :: Python :: 3.8
Classifier: Programming Language :: Python :: 3.9
Classifier: Programming Language :: Python :: 3.10
Classifier: Programming Language :: Python :: 3.11
Requires-Dist: dash (>=2.6.2,<3.0.0)
Project-URL: Repository, https://github.com/ellsphillips/govdash
